travitia_talk/__init__.py
travitia_talk/__main__.py
travitia_talk/chatbot.py
travitia_talk/context.py
travitia_talk/enums.py
travitia_talk/errors.py
travitia_talk/py.typed
travitia_talk/response.py
travitia_talk-0.0.1.dist-info/LICENSE
travitia_talk-0.0.1.dist-info/METADATA
travitia_talk-0.0.1.dist-info/WHEEL
travitia_talk-0.0.1.dist-info/top_level.txt
travitia_talk-0.0.1.dist-info/RECORD
