Metadata-Version: 2.1
Name: travitia-talk
Version: 0.0.1
Summary: ChatBot API wrapper for https://public-api.travitia.xyz/talk
Home-page: https://github.com/Fogapod/travitia-talk
Author: Eugene Ershov
Author-email: fogaprod@gmail.com
License: MIT
Platform: UNKNOWN
Classifier: Development Status :: 3 - Alpha
Classifier: Intended Audience :: Developers
Classifier: Programming Language :: Python
Classifier: Programming Language :: Python :: 3
Classifier: Programming Language :: Python :: 3.6
Classifier: Programming Language :: Python :: 3.7
Classifier: Programming Language :: Python :: 3.8
Classifier: Programming Language :: Python :: 3.9
Classifier: Programming Language :: Python :: Implementation :: CPython
Classifier: Programming Language :: Python :: Implementation :: PyPy
Classifier: Operating System :: OS Independent
Classifier: License :: OSI Approved :: MIT License
Classifier: Natural Language :: English
Classifier: Typing :: Typed
Requires-Python: >=3.6
Requires-Dist: aiohttp
